vancouver_watching/QGIS.py
vancouver_watching/README.py
vancouver_watching/__init__.py
vancouver_watching/__main__.py
vancouver_watching/config.env
vancouver_watching/env.py
vancouver_watching/host.py
vancouver_watching/logger.py
vancouver_watching/sample.env
vancouver_watching/urls.py
vancouver_watching/.abcli/actions.sh
vancouver_watching/.abcli/alias.sh
vancouver_watching/.abcli/detect.sh
vancouver_watching/.abcli/discover.sh
vancouver_watching/.abcli/ingest.sh
vancouver_watching/.abcli/list_targets.sh
vancouver_watching/.abcli/vancouver_watching.sh
vancouver_watching/.abcli/discovery/toronto.sh
vancouver_watching/.abcli/discovery/vancouver.sh
vancouver_watching/.abcli/tests/README.sh
vancouver_watching/.abcli/tests/discover.sh
vancouver_watching/.abcli/tests/discover_ingest_and_detect.sh
vancouver_watching/.abcli/tests/help.sh
vancouver_watching/.abcli/tests/list_targets.sh
vancouver_watching/.abcli/tests/version.sh
vancouver_watching/ai/__init__.py
vancouver_watching/ai/ultralytics.py
vancouver_watching/discover/__init__.py
vancouver_watching/discover/__main__.py
vancouver_watching/discover/targets.py
vancouver_watching/discover/testing.py
vancouver_watching/discover/toronto.py
vancouver_watching/discover/vancouver.py
vancouver_watching/help/__init__.py
vancouver_watching/help/__main__.py
vancouver_watching/help/detect.py
vancouver_watching/help/discover.py
vancouver_watching/help/functions.py
vancouver_watching/help/ingest.py
vancouver_watching/help/targets.py
vancouver_watching/target/__init__.py
vancouver_watching/target/__main__.py
vancouver_watching/target/classes.py
vancouver_watching/target/detection.py
vancouver_watching/target/ingest.py
vancouver_watching-4.36.1.dist-info/licenses/LICENSE
vancouver_watching-4.36.1.dist-info/METADATA
vancouver_watching-4.36.1.dist-info/WHEEL
vancouver_watching-4.36.1.dist-info/top_level.txt
vancouver_watching-4.36.1.dist-info/RECORD
